<?xml version="1.0" encoding="UTF-8"?>
<!-- generated: 2021-12-17T15:51:07+08:00 -->
<!-- generated by: Wen [??] -->
<adag xmlns="http://pegasus.isi.edu/schema/DAX" xmlns:xsi="http://www.w3.org/2001/XMLSchema-instance" xsi:schemaLocation="http://pegasus.isi.edu/schema/DAX http://pegasus.isi.edu/schema/dax-2.1.xsd" version="2.1" count="1" index="0" name="test" jobCount="100" fileCount="0" childCount="98">
<!-- part 1: list of all referenced files (may be empty) -->
<!-- part 2: definition of all jobs (at least one) -->
  <job id="ID00000" namespace="CyberShake" name="ZipPSA" version="1.0" runtime="0.53">
    <uses file="PeakVals_FFI_0_1_ID00003.bsa" link="input" register="false" transfer="false" optional="false" type="data" size="216"/>
    <uses file="PeakVals_FFI_0_1_ID00005.bsa" link="input" register="false" transfer="false" optional="false" type="data" size="216"/>
    <uses file="PeakVals_FFI_0_1_ID00007.bsa" link="input" register="false" transfer="false" optional="false" type="data" size="216"/>
    <uses file="PeakVals_FFI_0_1_ID00009.bsa" link="input" register="false" transfer="false" optional="false" type="data" size="216"/>
    <uses file="PeakVals_FFI_0_1_ID00011.bsa" link="input" register="false" transfer="false" optional="false" type="data" size="216"/>
    <uses file="PeakVals_FFI_0_1_ID00013.bsa" link="input" register="false" transfer="false" optional="false" type="data" size="216"/>
    <uses file="PeakVals_FFI_0_1_ID00015.bsa" link="input" register="false" transfer="false" optional="false" type="data" size="216"/>
    <uses file="PeakVals_FFI_0_1_ID00017.bsa" link="input" register="false" transfer="false" optional="false" type="data" size="216"/>
    <uses file="PeakVals_FFI_0_1_ID00019.bsa" link="input" register="false" transfer="false" optional="false" type="data" size="216"/>
    <uses file="PeakVals_FFI_0_1_ID00021.bsa" link="input" register="false" transfer="false" optional="false" type="data" size="216"/>
    <uses file="PeakVals_FFI_0_1_ID00023.bsa" link="input" register="false" transfer="false" optional="false" type="data" size="216"/>
    <uses file="PeakVals_FFI_0_1_ID00025.bsa" link="input" register="false" transfer="false" optional="false" type="data" size="216"/>
    <uses file="PeakVals_FFI_0_1_ID00027.bsa" link="input" register="false" transfer="false" optional="false" type="data" size="216"/>
    <uses file="PeakVals_FFI_0_1_ID00029.bsa" link="input" register="false" transfer="false" optional="false" type="data" size="216"/>
    <uses file="PeakVals_FFI_0_1_ID00031.bsa" link="input" register="false" transfer="false" optional="false" type="data" size="216"/>
    <uses file="PeakVals_FFI_0_1_ID00033.bsa" link="input" register="false" transfer="false" optional="false" type="data" size="216"/>
    <uses file="PeakVals_FFI_0_1_ID00035.bsa" link="input" register="false" transfer="false" optional="false" type="data" size="216"/>
    <uses file="PeakVals_FFI_0_1_ID00037.bsa" link="input" register="false" transfer="false" optional="false" type="data" size="216"/>
    <uses file="PeakVals_FFI_0_1_ID00039.bsa" link="input" register="false" transfer="false" optional="false" type="data" size="216"/>
    <uses file="PeakVals_FFI_0_1_ID00041.bsa" link="input" register="false" transfer="false" optional="false" type="data" size="216"/>
    <uses file="PeakVals_FFI_0_1_ID00043.bsa" link="input" register="false" transfer="false" optional="false" type="data" size="216"/>
    <uses file="PeakVals_FFI_0_1_ID00045.bsa" link="input" register="false" transfer="false" optional="false" type="data" size="216"/>
    <uses file="PeakVals_FFI_0_2_ID00048.bsa" link="input" register="false" transfer="false" optional="false" type="data" size="216"/>
    <uses file="PeakVals_FFI_0_2_ID00050.bsa" link="input" register="false" transfer="false" optional="false" type="data" size="216"/>
    <uses file="PeakVals_FFI_0_2_ID00052.bsa" link="input" register="false" transfer="false" optional="false" type="data" size="216"/>
    <uses file="PeakVals_FFI_0_2_ID00054.bsa" link="input" register="false" transfer="false" optional="false" type="data" size="216"/>
    <uses file="PeakVals_FFI_0_2_ID00056.bsa" link="input" register="false" transfer="false" optional="false" type="data" size="216"/>
    <uses file="PeakVals_FFI_0_2_ID00058.bsa" link="input" register="false" transfer="false" optional="false" type="data" size="216"/>
    <uses file="PeakVals_FFI_0_2_ID00060.bsa" link="input" register="false" transfer="false" optional="false" type="data" size="216"/>
    <uses file="PeakVals_FFI_0_2_ID00062.bsa" link="input" register="false" transfer="false" optional="false" type="data" size="216"/>
    <uses file="PeakVals_FFI_0_2_ID00064.bsa" link="input" register="false" transfer="false" optional="false" type="data" size="216"/>
    <uses file="PeakVals_FFI_0_2_ID00066.bsa" link="input" register="false" transfer="false" optional="false" type="data" size="216"/>
    <uses file="PeakVals_FFI_0_2_ID00068.bsa" link="input" register="false" transfer="false" optional="false" type="data" size="216"/>
    <uses file="PeakVals_FFI_0_2_ID00070.bsa" link="input" register="false" transfer="false" optional="false" type="data" size="216"/>
    <uses file="PeakVals_FFI_0_2_ID00072.bsa" link="input" register="false" transfer="false" optional="false" type="data" size="216"/>
    <uses file="PeakVals_FFI_0_2_ID00074.bsa" link="input" register="false" transfer="false" optional="false" type="data" size="216"/>
    <uses file="PeakVals_FFI_0_2_ID00076.bsa" link="input" register="false" transfer="false" optional="false" type="data" size="216"/>
    <uses file="PeakVals_FFI_0_2_ID00078.bsa" link="input" register="false" transfer="false" optional="false" type="data" size="216"/>
    <uses file="PeakVals_FFI_0_2_ID00080.bsa" link="input" register="false" transfer="false" optional="false" type="data" size="216"/>
    <uses file="PeakVals_FFI_0_2_ID00082.bsa" link="input" register="false" transfer="false" optional="false" type="data" size="216"/>
    <uses file="PeakVals_FFI_0_2_ID00084.bsa" link="input" register="false" transfer="false" optional="false" type="data" size="216"/>
    <uses file="PeakVals_FFI_0_2_ID00086.bsa" link="input" register="false" transfer="false" optional="false" type="data" size="216"/>
    <uses file="PeakVals_FFI_0_2_ID00088.bsa" link="input" register="false" transfer="false" optional="false" type="data" size="216"/>
    <uses file="PeakVals_FFI_0_2_ID00090.bsa" link="input" register="false" transfer="false" optional="false" type="data" size="216"/>
    <uses file="PeakVals_FFI_0_2_ID00092.bsa" link="input" register="false" transfer="false" optional="false" type="data" size="216"/>
    <uses file="PeakVals_FFI_0_2_ID00094.bsa" link="input" register="false" transfer="false" optional="false" type="data" size="216"/>
    <uses file="PeakVals_FFI_0_2_ID00096.bsa" link="input" register="false" transfer="false" optional="false" type="data" size="216"/>
    <uses file="PeakVals_FFI_0_2_ID00098.bsa" link="input" register="false" transfer="false" optional="false" type="data" size="216"/>
    <uses file="Cybershake_PSA.zip" link="output" register="true" transfer="true" optional="false" type="data" size="1484"/>
  </job>
  <job id="ID00001" namespace="CyberShake" name="ZipSeis" version="1.0" runtime="0.63">
    <uses file="Seismogram_FFI_0_1_ID00003.grm" link="input" register="false" transfer="false" optional="false" type="data" size="24000"/>
    <uses file="Seismogram_FFI_0_1_ID00005.grm" link="input" register="false" transfer="false" optional="false" type="data" size="24000"/>
    <uses file="Seismogram_FFI_0_1_ID00007.grm" link="input" register="false" transfer="false" optional="false" type="data" size="24000"/>
    <uses file="Seismogram_FFI_0_1_ID00009.grm" link="input" register="false" transfer="false" optional="false" type="data" size="24000"/>
    <uses file="Seismogram_FFI_0_1_ID00011.grm" link="input" register="false" transfer="false" optional="false" type="data" size="24000"/>
    <uses file="Seismogram_FFI_0_1_ID00013.grm" link="input" register="false" transfer="false" optional="false" type="data" size="24000"/>
    <uses file="Seismogram_FFI_0_1_ID00015.grm" link="input" register="false" transfer="false" optional="false" type="data" size="24000"/>
    <uses file="Seismogram_FFI_0_1_ID00017.grm" link="input" register="false" transfer="false" optional="false" type="data" size="24000"/>
    <uses file="Seismogram_FFI_0_1_ID00019.grm" link="input" register="false" transfer="false" optional="false" type="data" size="24000"/>
    <uses file="Seismogram_FFI_0_1_ID00021.grm" link="input" register="false" transfer="false" optional="false" type="data" size="24000"/>
    <uses file="Seismogram_FFI_0_1_ID00023.grm" link="input" register="false" transfer="false" optional="false" type="data" size="24000"/>
    <uses file="Seismogram_FFI_0_1_ID00025.grm" link="input" register="false" transfer="false" optional="false" type="data" size="24000"/>
    <uses file="Seismogram_FFI_0_1_ID00027.grm" link="input" register="false" transfer="false" optional="false" type="data" size="24000"/>
    <uses file="Seismogram_FFI_0_1_ID00029.grm" link="input" register="false" transfer="false" optional="false" type="data" size="24000"/>
    <uses file="Seismogram_FFI_0_1_ID00031.grm" link="input" register="false" transfer="false" optional="false" type="data" size="24000"/>
    <uses file="Seismogram_FFI_0_1_ID00033.grm" link="input" register="false" transfer="false" optional="false" type="data" size="24000"/>
    <uses file="Seismogram_FFI_0_1_ID00035.grm" link="input" register="false" transfer="false" optional="false" type="data" size="24000"/>
    <uses file="Seismogram_FFI_0_1_ID00037.grm" link="input" register="false" transfer="false" optional="false" type="data" size="24000"/>
    <uses file="Seismogram_FFI_0_1_ID00039.grm" link="input" register="false" transfer="false" optional="false" type="data" size="24000"/>
    <uses file="Seismogram_FFI_0_1_ID00041.grm" link="input" register="false" transfer="false" optional="false" type="data" size="24000"/>
    <uses file="Seismogram_FFI_0_1_ID00043.grm" link="input" register="false" transfer="false" optional="false" type="data" size="24000"/>
    <uses file="Seismogram_FFI_0_1_ID00045.grm" link="input" register="false" transfer="false" optional="false" type="data" size="24000"/>
    <uses file="Seismogram_FFI_0_2_ID00048.grm" link="input" register="false" transfer="false" optional="false" type="data" size="24000"/>
    <uses file="Seismogram_FFI_0_2_ID00050.grm" link="input" register="false" transfer="false" optional="false" type="data" size="24000"/>
    <uses file="Seismogram_FFI_0_2_ID00052.grm" link="input" register="false" transfer="false" optional="false" type="data" size="24000"/>
    <uses file="Seismogram_FFI_0_2_ID00054.grm" link="input" register="false" transfer="false" optional="false" type="data" size="24000"/>
    <uses file="Seismogram_FFI_0_2_ID00056.grm" link="input" register="false" transfer="false" optional="false" type="data" size="24000"/>
    <uses file="Seismogram_FFI_0_2_ID00058.grm" link="input" register="false" transfer="false" optional="false" type="data" size="24000"/>
    <uses file="Seismogram_FFI_0_2_ID00060.grm" link="input" register="false" transfer="false" optional="false" type="data" size="24000"/>
    <uses file="Seismogram_FFI_0_2_ID00062.grm" link="input" register="false" transfer="false" optional="false" type="data" size="24000"/>
    <uses file="Seismogram_FFI_0_2_ID00064.grm" link="input" register="false" transfer="false" optional="false" type="data" size="24000"/>
    <uses file="Seismogram_FFI_0_2_ID00066.grm" link="input" register="false" transfer="false" optional="false" type="data" size="24000"/>
    <uses file="Seismogram_FFI_0_2_ID00068.grm" link="input" register="false" transfer="false" optional="false" type="data" size="24000"/>
    <uses file="Seismogram_FFI_0_2_ID00070.grm" link="input" register="false" transfer="false" optional="false" type="data" size="24000"/>
    <uses file="Seismogram_FFI_0_2_ID00072.grm" link="input" register="false" transfer="false" optional="false" type="data" size="24000"/>
    <uses file="Seismogram_FFI_0_2_ID00074.grm" link="input" register="false" transfer="false" optional="false" type="data" size="24000"/>
    <uses file="Seismogram_FFI_0_2_ID00076.grm" link="input" register="false" transfer="false" optional="false" type="data" size="24000"/>
    <uses file="Seismogram_FFI_0_2_ID00078.grm" link="input" register="false" transfer="false" optional="false" type="data" size="24000"/>
    <uses file="Seismogram_FFI_0_2_ID00080.grm" link="input" register="false" transfer="false" optional="false" type="data" size="24000"/>
    <uses file="Seismogram_FFI_0_2_ID00082.grm" link="input" register="false" transfer="false" optional="false" type="data" size="24000"/>
    <uses file="Seismogram_FFI_0_2_ID00084.grm" link="input" register="false" transfer="false" optional="false" type="data" size="24000"/>
    <uses file="Seismogram_FFI_0_2_ID00086.grm" link="input" register="false" transfer="false" optional="false" type="data" size="24000"/>
    <uses file="Seismogram_FFI_0_2_ID00088.grm" link="input" register="false" transfer="false" optional="false" type="data" size="24000"/>
    <uses file="Seismogram_FFI_0_2_ID00090.grm" link="input" register="false" transfer="false" optional="false" type="data" size="24000"/>
    <uses file="Seismogram_FFI_0_2_ID00092.grm" link="input" register="false" transfer="false" optional="false" type="data" size="24000"/>
    <uses file="Seismogram_FFI_0_2_ID00094.grm" link="input" register="false" transfer="false" optional="false" type="data" size="24000"/>
    <uses file="Seismogram_FFI_0_2_ID00096.grm" link="input" register="false" transfer="false" optional="false" type="data" size="24000"/>
    <uses file="Seismogram_FFI_0_2_ID00098.grm" link="input" register="false" transfer="false" optional="false" type="data" size="24000"/>
    <uses file="Cybershake_Seismograms.zip" link="output" register="true" transfer="true" optional="false" type="data" size="143681"/>
  </job>
  <job id="ID00002" namespace="CyberShake" name="ExtractSGT" version="1.0" runtime="159.06">
    <uses file="FFI_0_1_fx.sgt" link="input" register="true" transfer="true" optional="false" type="data" size="20076800097"/>
    <uses file="FFI_0_1_fy.sgt" link="input" register="true" transfer="true" optional="false" type="data" size="20076800097"/>
    <uses file="FFI_0_1_subfx.sgt" link="output" register="false" transfer="false" optional="false" type="data" size="229662543"/>
    <uses file="FFI_0_1_subfy.sgt" link="output" register="false" transfer="false" optional="false" type="data" size="229662543"/>
    <uses file="FFI_0_1_txt.variation-s01138-h01827" link="input" register="true" transfer="true" optional="false" type="data" size="5412881"/>
  </job>
  <job id="ID00003" namespace="CyberShake" name="SeismogramSynthesis" version="1.0" runtime="33.65">
    <uses file="FFI_0_1_txt.variation-s07438-h03377" link="input" register="true" transfer="true" optional="false" type="data" size="2441811"/>
    <uses file="FFI_0_1_subfx.sgt" link="input" register="false" transfer="false" optional="false" type="data" size="229662543"/>
    <uses file="FFI_0_1_subfy.sgt" link="input" register="false" transfer="false" optional="false" type="data" size="229662543"/>
    <uses file="Seismogram_FFI_0_1_ID00003.grm" link="output" register="false" transfer="false" optional="false" type="data" size="24000"/>
  </job>
  <job id="ID00004" namespace="CyberShake" name="PeakValCalcOkaya" version="1.0" runtime="1.25">
    <uses file="Seismogram_FFI_0_1_ID00003.grm" link="input" register="false" transfer="false" optional="false" type="data" size="24000"/>
    <uses file="PeakVals_FFI_0_1_ID00003.bsa" link="output" register="false" transfer="false" optional="false" type="data" size="216"/>
  </job>
  <job id="ID00005" namespace="CyberShake" name="SeismogramSynthesis" version="1.0" runtime="40.95">
    <uses file="FFI_0_1_txt.variation-s05137-h00825" link="input" register="true" transfer="true" optional="false" type="data" size="2001890"/>
    <uses file="FFI_0_1_subfx.sgt" link="input" register="false" transfer="false" optional="false" type="data" size="152137435"/>
    <uses file="FFI_0_1_subfy.sgt" link="input" register="false" transfer="false" optional="false" type="data" size="152137435"/>
    <uses file="Seismogram_FFI_0_1_ID00005.grm" link="output" register="false" transfer="false" optional="false" type="data" size="24000"/>
  </job>
  <job id="ID00006" namespace="CyberShake" name="PeakValCalcOkaya" version="1.0" runtime="1.20">
    <uses file="Seismogram_FFI_0_1_ID00005.grm" link="input" register="false" transfer="false" optional="false" type="data" size="24000"/>
    <uses file="PeakVals_FFI_0_1_ID00005.bsa" link="output" register="false" transfer="false" optional="false" type="data" size="216"/>
  </job>
  <job id="ID00007" namespace="CyberShake" name="SeismogramSynthesis" version="1.0" runtime="24.79">
    <uses file="FFI_0_1_txt.variation-s05755-h01153" link="input" register="true" transfer="true" optional="false" type="data" size="3442580"/>
    <uses file="FFI_0_1_subfx.sgt" link="input" register="false" transfer="false" optional="false" type="data" size="311944947"/>
    <uses file="FFI_0_1_subfy.sgt" link="input" register="false" transfer="false" optional="false" type="data" size="311944947"/>
    <uses file="Seismogram_FFI_0_1_ID00007.grm" link="output" register="false" transfer="false" optional="false" type="data" size="24000"/>
  </job>
  <job id="ID00008" namespace="CyberShake" name="PeakValCalcOkaya" version="1.0" runtime="0.70">
    <uses file="Seismogram_FFI_0_1_ID00007.grm" link="input" register="false" transfer="false" optional="false" type="data" size="24000"/>
    <uses file="PeakVals_FFI_0_1_ID00007.bsa" link="output" register="false" transfer="false" optional="false" type="data" size="216"/>
  </job>
  <job id="ID00009" namespace="CyberShake" name="SeismogramSynthesis" version="1.0" runtime="32.65">
    <uses file="FFI_0_1_txt.variation-s02342-h03265" link="input" register="true" transfer="true" optional="false" type="data" size="3105978"/>
    <uses file="FFI_0_1_subfx.sgt" link="input" register="false" transfer="false" optional="false" type="data" size="279188293"/>
    <uses file="FFI_0_1_subfy.sgt" link="input" register="false" transfer="false" optional="false" type="data" size="279188293"/>
    <uses file="Seismogram_FFI_0_1_ID00009.grm" link="output" register="false" transfer="false" optional="false" type="data" size="24000"/>
  </job>
  <job id="ID00010" namespace="CyberShake" name="PeakValCalcOkaya" version="1.0" runtime="1.19">
    <uses file="Seismogram_FFI_0_1_ID00009.grm" link="input" register="false" transfer="false" optional="false" type="data" size="24000"/>
    <uses file="PeakVals_FFI_0_1_ID00009.bsa" link="output" register="false" transfer="false" optional="false" type="data" size="216"/>
  </job>
  <job id="ID00011" namespace="CyberShake" name="SeismogramSynthesis" version="1.0" runtime="40.19">
    <uses file="FFI_0_1_txt.variation-s08988-h06705" link="input" register="true" transfer="true" optional="false" type="data" size="2991726"/>
    <uses file="FFI_0_1_subfx.sgt" link="input" register="false" transfer="false" optional="false" type="data" size="179170006"/>
    <uses file="FFI_0_1_subfy.sgt" link="input" register="false" transfer="false" optional="false" type="data" size="179170006"/>
    <uses file="Seismogram_FFI_0_1_ID00011.grm" link="output" register="false" transfer="false" optional="false" type="data" size="24000"/>
  </job>
  <job id="ID00012" namespace="CyberShake" name="PeakValCalcOkaya" version="1.0" runtime="0.61">
    <uses file="Seismogram_FFI_0_1_ID00011.grm" link="input" register="false" transfer="false" optional="false" type="data" size="24000"/>
    <uses file="PeakVals_FFI_0_1_ID00011.bsa" link="output" register="false" transfer="false" optional="false" type="data" size="216"/>
  </job>
  <job id="ID00013" namespace="CyberShake" name="SeismogramSynthesis" version="1.0" runtime="51.60">
    <uses file="FFI_0_1_txt.variation-s05866-h03919" link="input" register="true" transfer="true" optional="false" type="data" size="3460371"/>
    <uses file="FFI_0_1_subfx.sgt" link="input" register="false" transfer="false" optional="false" type="data" size="128370362"/>
    <uses file="FFI_0_1_subfy.sgt" link="input" register="false" transfer="false" optional="false" type="data" size="128370362"/>
    <uses file="Seismogram_FFI_0_1_ID00013.grm" link="output" register="false" transfer="false" optional="false" type="data" size="24000"/>
  </job>
  <job id="ID00014" namespace="CyberShake" name="PeakValCalcOkaya" version="1.0" runtime="1.55">
    <uses file="Seismogram_FFI_0_1_ID00013.grm" link="input" register="false" transfer="false" optional="false" type="data" size="24000"/>
    <uses file="PeakVals_FFI_0_1_ID00013.bsa" link="output" register="false" transfer="false" optional="false" type="data" size="216"/>
  </job>
  <job id="ID00015" namespace="CyberShake" name="SeismogramSynthesis" version="1.0" runtime="28.32">
    <uses file="FFI_0_1_txt.variation-s02107-h00244" link="input" register="true" transfer="true" optional="false" type="data" size="2045404"/>
    <uses file="FFI_0_1_subfx.sgt" link="input" register="false" transfer="false" optional="false" type="data" size="233145258"/>
    <uses file="FFI_0_1_subfy.sgt" link="input" register="false" transfer="false" optional="false" type="data" size="233145258"/>
    <uses file="Seismogram_FFI_0_1_ID00015.grm" link="output" register="false" transfer="false" optional="false" type="data" size="24000"/>
  </job>
  <job id="ID00016" namespace="CyberShake" name="PeakValCalcOkaya" version="1.0" runtime="1.49">
    <uses file="Seismogram_FFI_0_1_ID00015.grm" link="input" register="false" transfer="false" optional="false" type="data" size="24000"/>
    <uses file="PeakVals_FFI_0_1_ID00015.bsa" link="output" register="false" transfer="false" optional="false" type="data" size="216"/>
  </job>
  <job id="ID00017" namespace="CyberShake" name="SeismogramSynthesis" version="1.0" runtime="31.30">
    <uses file="FFI_0_1_txt.variation-s05083-h03402" link="input" register="true" transfer="true" optional="false" type="data" size="4235853"/>
    <uses file="FFI_0_1_subfx.sgt" link="input" register="false" transfer="false" optional="false" type="data" size="211311416"/>
    <uses file="FFI_0_1_subfy.sgt" link="input" register="false" transfer="false" optional="false" type="data" size="211311416"/>
    <uses file="Seismogram_FFI_0_1_ID00017.grm" link="output" register="false" transfer="false" optional="false" type="data" size="24000"/>
  </job>
  <job id="ID00018" namespace="CyberShake" name="PeakValCalcOkaya" version="1.0" runtime="0.87">
    <uses file="Seismogram_FFI_0_1_ID00017.grm" link="input" register="false" transfer="false" optional="false" type="data" size="24000"/>
    <uses file="PeakVals_FFI_0_1_ID00017.bsa" link="output" register="false" transfer="false" optional="false" type="data" size="216"/>
  </job>
  <job id="ID00019" namespace="CyberShake" name="SeismogramSynthesis" version="1.0" runtime="46.61">
    <uses file="FFI_0_1_txt.variation-s04767-h08201" link="input" register="true" transfer="true" optional="false" type="data" size="3494394"/>
    <uses file="FFI_0_1_subfx.sgt" link="input" register="false" transfer="false" optional="false" type="data" size="121554645"/>
    <uses file="FFI_0_1_subfy.sgt" link="input" register="false" transfer="false" optional="false" type="data" size="121554645"/>
    <uses file="Seismogram_FFI_0_1_ID00019.grm" link="output" register="false" transfer="false" optional="false" type="data" size="24000"/>
  </job>
  <job id="ID00020" namespace="CyberShake" name="PeakValCalcOkaya" version="1.0" runtime="0.57">
    <uses file="Seismogram_FFI_0_1_ID00019.grm" link="input" register="false" transfer="false" optional="false" type="data" size="24000"/>
    <uses file="PeakVals_FFI_0_1_ID00019.bsa" link="output" register="false" transfer="false" optional="false" type="data" size="216"/>
  </job>
  <job id="ID00021" namespace="CyberShake" name="SeismogramSynthesis" version="1.0" runtime="36.00">
    <uses file="FFI_0_1_txt.variation-s08498-h08457" link="input" register="true" transfer="true" optional="false" type="data" size="1864623"/>
    <uses file="FFI_0_1_subfx.sgt" link="input" register="false" transfer="false" optional="false" type="data" size="313010999"/>
    <uses file="FFI_0_1_subfy.sgt" link="input" register="false" transfer="false" optional="false" type="data" size="313010999"/>
    <uses file="Seismogram_FFI_0_1_ID00021.grm" link="output" register="false" transfer="false" optional="false" type="data" size="24000"/>
  </job>
  <job id="ID00022" namespace="CyberShake" name="PeakValCalcOkaya" version="1.0" runtime="1.51">
    <uses file="Seismogram_FFI_0_1_ID00021.grm" link="input" register="false" transfer="false" optional="false" type="data" size="24000"/>
    <uses file="PeakVals_FFI_0_1_ID00021.bsa" link="output" register="false" transfer="false" optional="false" type="data" size="216"/>
  </job>
  <job id="ID00023" namespace="CyberShake" name="SeismogramSynthesis" version="1.0" runtime="59.39">
    <uses file="FFI_0_1_txt.variation-s09670-h02592" link="input" register="true" transfer="true" optional="false" type="data" size="2675939"/>
    <uses file="FFI_0_1_subfx.sgt" link="input" register="false" transfer="false" optional="false" type="data" size="260836672"/>
    <uses file="FFI_0_1_subfy.sgt" link="input" register="false" transfer="false" optional="false" type="data" size="260836672"/>
    <uses file="Seismogram_FFI_0_1_ID00023.grm" link="output" register="false" transfer="false" optional="false" type="data" size="24000"/>
  </job>
  <job id="ID00024" namespace="CyberShake" name="PeakValCalcOkaya" version="1.0" runtime="1.22">
    <uses file="Seismogram_FFI_0_1_ID00023.grm" link="input" register="false" transfer="false" optional="false" type="data" size="24000"/>
    <uses file="PeakVals_FFI_0_1_ID00023.bsa" link="output" register="false" transfer="false" optional="false" type="data" size="216"/>
  </job>
  <job id="ID00025" namespace="CyberShake" name="SeismogramSynthesis" version="1.0" runtime="44.27">
    <uses file="FFI_0_1_txt.variation-s02165-h00823" link="input" register="true" transfer="true" optional="false" type="data" size="2146073"/>
    <uses file="FFI_0_1_subfx.sgt" link="input" register="false" transfer="false" optional="false" type="data" size="221356825"/>
    <uses file="FFI_0_1_subfy.sgt" link="input" register="false" transfer="false" optional="false" type="data" size="221356825"/>
    <uses file="Seismogram_FFI_0_1_ID00025.grm" link="output" register="false" transfer="false" optional="false" type="data" size="24000"/>
  </job>
  <job id="ID00026" namespace="CyberShake" name="PeakValCalcOkaya" version="1.0" runtime="0.86">
    <uses file="Seismogram_FFI_0_1_ID00025.grm" link="input" register="false" transfer="false" optional="false" type="data" size="24000"/>
    <uses file="PeakVals_FFI_0_1_ID00025.bsa" link="output" register="false" transfer="false" optional="false" type="data" size="216"/>
  </job>
  <job id="ID00027" namespace="CyberShake" name="SeismogramSynthesis" version="1.0" runtime="31.82">
    <uses file="FFI_0_1_txt.variation-s07448-h01996" link="input" register="true" transfer="true" optional="false" type="data" size="3560944"/>
    <uses file="FFI_0_1_subfx.sgt" link="input" register="false" transfer="false" optional="false" type="data" size="153407941"/>
    <uses file="FFI_0_1_subfy.sgt" link="input" register="false" transfer="false" optional="false" type="data" size="153407941"/>
    <uses file="Seismogram_FFI_0_1_ID00027.grm" link="output" register="false" transfer="false" optional="false" type="data" size="24000"/>
  </job>
  <job id="ID00028" namespace="CyberShake" name="PeakValCalcOkaya" version="1.0" runtime="0.81">
    <uses file="Seismogram_FFI_0_1_ID00027.grm" link="input" register="false" transfer="false" optional="false" type="data" size="24000"/>
    <uses file="PeakVals_FFI_0_1_ID00027.bsa" link="output" register="false" transfer="false" optional="false" type="data" size="216"/>
  </job>
  <job id="ID00029" namespace="CyberShake" name="SeismogramSynthesis" version="1.0" runtime="23.27">
    <uses file="FFI_0_1_txt.variation-s00511-h01447" link="input" register="true" transfer="true" optional="false" type="data" size="2579177"/>
    <uses file="FFI_0_1_subfx.sgt" link="input" register="false" transfer="false" optional="false" type="data" size="266308043"/>
    <uses file="FFI_0_1_subfy.sgt" link="input" register="false" transfer="false" optional="false" type="data" size="266308043"/>
    <uses file="Seismogram_FFI_0_1_ID00029.grm" link="output" register="false" transfer="false" optional="false" type="data" size="24000"/>
  </job>
  <job id="ID00030" namespace="CyberShake" name="PeakValCalcOkaya" version="1.0" runtime="1.30">
    <uses file="Seismogram_FFI_0_1_ID00029.grm" link="input" register="false" transfer="false" optional="false" type="data" size="24000"/>
    <uses file="PeakVals_FFI_0_1_ID00029.bsa" link="output" register="false" transfer="false" optional="false" type="data" size="216"/>
  </job>
  <job id="ID00031" namespace="CyberShake" name="SeismogramSynthesis" version="1.0" runtime="57.00">
    <uses file="FFI_0_1_txt.variation-s05299-h09563" link="input" register="true" transfer="true" optional="false" type="data" size="4252658"/>
    <uses file="FFI_0_1_subfx.sgt" link="input" register="false" transfer="false" optional="false" type="data" size="144253805"/>
    <uses file="FFI_0_1_subfy.sgt" link="input" register="false" transfer="false" optional="false" type="data" size="144253805"/>
    <uses file="Seismogram_FFI_0_1_ID00031.grm" link="output" register="false" transfer="false" optional="false" type="data" size="24000"/>
  </job>
  <job id="ID00032" namespace="CyberShake" name="PeakValCalcOkaya" version="1.0" runtime="0.71">
    <uses file="Seismogram_FFI_0_1_ID00031.grm" link="input" register="false" transfer="false" optional="false" type="data" size="24000"/>
    <uses file="PeakVals_FFI_0_1_ID00031.bsa" link="output" register="false" transfer="false" optional="false" type="data" size="216"/>
  </job>
  <job id="ID00033" namespace="CyberShake" name="SeismogramSynthesis" version="1.0" runtime="36.73">
    <uses file="FFI_0_1_txt.variation-s06609-h00768" link="input" register="true" transfer="true" optional="false" type="data" size="3941238"/>
    <uses file="FFI_0_1_subfx.sgt" link="input" register="false" transfer="false" optional="false" type="data" size="226240950"/>
    <uses file="FFI_0_1_subfy.sgt" link="input" register="false" transfer="false" optional="false" type="data" size="226240950"/>
    <uses file="Seismogram_FFI_0_1_ID00033.grm" link="output" register="false" transfer="false" optional="false" type="data" size="24000"/>
  </job>
  <job id="ID00034" namespace="CyberShake" name="PeakValCalcOkaya" version="1.0" runtime="0.76">
    <uses file="Seismogram_FFI_0_1_ID00033.grm" link="input" register="false" transfer="false" optional="false" type="data" size="24000"/>
    <uses file="PeakVals_FFI_0_1_ID00033.bsa" link="output" register="false" transfer="false" optional="false" type="data" size="216"/>
  </job>
  <job id="ID00035" namespace="CyberShake" name="SeismogramSynthesis" version="1.0" runtime="61.35">
    <uses file="FFI_0_1_txt.variation-s01277-h05884" link="input" register="true" transfer="true" optional="false" type="data" size="5028289"/>
    <uses file="FFI_0_1_subfx.sgt" link="input" register="false" transfer="false" optional="false" type="data" size="248692743"/>
    <uses file="FFI_0_1_subfy.sgt" link="input" register="false" transfer="false" optional="false" type="data" size="248692743"/>
    <uses file="Seismogram_FFI_0_1_ID00035.grm" link="output" register="false" transfer="false" optional="false" type="data" size="24000"/>
  </job>
  <job id="ID00036" namespace="CyberShake" name="PeakValCalcOkaya" version="1.0" runtime="1.08">
    <uses file="Seismogram_FFI_0_1_ID00035.grm" link="input" register="false" transfer="false" optional="false" type="data" size="24000"/>
    <uses file="PeakVals_FFI_0_1_ID00035.bsa" link="output" register="false" transfer="false" optional="false" type="data" size="216"/>
  </job>
  <job id="ID00037" namespace="CyberShake" name="SeismogramSynthesis" version="1.0" runtime="41.13">
    <uses file="FFI_0_1_txt.variation-s09071-h07556" link="input" register="true" transfer="true" optional="false" type="data" size="4858776"/>
    <uses file="FFI_0_1_subfx.sgt" link="input" register="false" transfer="false" optional="false" type="data" size="250994047"/>
    <uses file="FFI_0_1_subfy.sgt" link="input" register="false" transfer="false" optional="false" type="data" size="250994047"/>
    <uses file="Seismogram_FFI_0_1_ID00037.grm" link="output" register="false" transfer="false" optional="false" type="data" size="24000"/>
  </job>
  <job id="ID00038" namespace="CyberShake" name="PeakValCalcOkaya" version="1.0" runtime="0.61">
    <uses file="Seismogram_FFI_0_1_ID00037.grm" link="input" register="false" transfer="false" optional="false" type="data" size="24000"/>
    <uses file="PeakVals_FFI_0_1_ID00037.bsa" link="output" register="false" transfer="false" optional="false" type="data" size="216"/>
  </job>
  <job id="ID00039" namespace="CyberShake" name="SeismogramSynthesis" version="1.0" runtime="28.63">
    <uses file="FFI_0_1_txt.variation-s03276-h03550" link="input" register="true" transfer="true" optional="false" type="data" size="5074902"/>
    <uses file="FFI_0_1_subfx.sgt" link="input" register="false" transfer="false" optional="false" type="data" size="342361905"/>
    <uses file="FFI_0_1_subfy.sgt" link="input" register="false" transfer="false" optional="false" type="data" size="342361905"/>
    <uses file="Seismogram_FFI_0_1_ID00039.grm" link="output" register="false" transfer="false" optional="false" type="data" size="24000"/>
  </job>
  <job id="ID00040" namespace="CyberShake" name="PeakValCalcOkaya" version="1.0" runtime="1.53">
    <uses file="Seismogram_FFI_0_1_ID00039.grm" link="input" register="false" transfer="false" optional="false" type="data" size="24000"/>
    <uses file="PeakVals_FFI_0_1_ID00039.bsa" link="output" register="false" transfer="false" optional="false" type="data" size="216"/>
  </job>
  <job id="ID00041" namespace="CyberShake" name="SeismogramSynthesis" version="1.0" runtime="48.30">
    <uses file="FFI_0_1_txt.variation-s02482-h05379" link="input" register="true" transfer="true" optional="false" type="data" size="3005389"/>
    <uses file="FFI_0_1_subfx.sgt" link="input" register="false" transfer="false" optional="false" type="data" size="194333055"/>
    <uses file="FFI_0_1_subfy.sgt" link="input" register="false" transfer="false" optional="false" type="data" size="194333055"/>
    <uses file="Seismogram_FFI_0_1_ID00041.grm" link="output" register="false" transfer="false" optional="false" type="data" size="24000"/>
  </job>
  <job id="ID00042" namespace="CyberShake" name="PeakValCalcOkaya" version="1.0" runtime="1.19">
    <uses file="Seismogram_FFI_0_1_ID00041.grm" link="input" register="false" transfer="false" optional="false" type="data" size="24000"/>
    <uses file="PeakVals_FFI_0_1_ID00041.bsa" link="output" register="false" transfer="false" optional="false" type="data" size="216"/>
  </job>
  <job id="ID00043" namespace="CyberShake" name="SeismogramSynthesis" version="1.0" runtime="32.21">
    <uses file="FFI_0_1_txt.variation-s00605-h02400" link="input" register="true" transfer="true" optional="false" type="data" size="5060110"/>
    <uses file="FFI_0_1_subfx.sgt" link="input" register="false" transfer="false" optional="false" type="data" size="298592159"/>
    <uses file="FFI_0_1_subfy.sgt" link="input" register="false" transfer="false" optional="false" type="data" size="298592159"/>
    <uses file="Seismogram_FFI_0_1_ID00043.grm" link="output" register="false" transfer="false" optional="false" type="data" size="24000"/>
  </job>
  <job id="ID00044" namespace="CyberShake" name="PeakValCalcOkaya" version="1.0" runtime="0.75">
    <uses file="Seismogram_FFI_0_1_ID00043.grm" link="input" register="false" transfer="false" optional="false" type="data" size="24000"/>
    <uses file="PeakVals_FFI_0_1_ID00043.bsa" link="output" register="false" transfer="false" optional="false" type="data" size="216"/>
  </job>
  <job id="ID00045" namespace="CyberShake" name="SeismogramSynthesis" version="1.0" runtime="30.41">
    <uses file="FFI_0_1_txt.variation-s01138-h01827" link="input" register="true" transfer="true" optional="false" type="data" size="5412881"/>
    <uses file="FFI_0_1_subfx.sgt" link="input" register="false" transfer="false" optional="false" type="data" size="326313229"/>
    <uses file="FFI_0_1_subfy.sgt" link="input" register="false" transfer="false" optional="false" type="data" size="326313229"/>
    <uses file="Seismogram_FFI_0_1_ID00045.grm" link="output" register="false" transfer="false" optional="false" type="data" size="24000"/>
  </job>
  <job id="ID00046" namespace="CyberShake" name="PeakValCalcOkaya" version="1.0" runtime="1.10">
    <uses file="Seismogram_FFI_0_1_ID00045.grm" link="input" register="false" transfer="false" optional="false" type="data" size="24000"/>
    <uses file="PeakVals_FFI_0_1_ID00045.bsa" link="output" register="false" transfer="false" optional="false" type="data" size="216"/>
  </job>
  <job id="ID00047" namespace="CyberShake" name="ExtractSGT" version="1.0" runtime="120.23">
    <uses file="FFI_0_2_fx.sgt" link="input" register="true" transfer="true" optional="false" type="data" size="20179405897"/>
    <uses file="FFI_0_2_fy.sgt" link="input" register="true" transfer="true" optional="false" type="data" size="20179405897"/>
    <uses file="FFI_0_2_subfx.sgt" link="output" register="false" transfer="false" optional="false" type="data" size="217892808"/>
    <uses file="FFI_0_2_subfy.sgt" link="output" register="false" transfer="false" optional="false" type="data" size="217892808"/>
    <uses file="FFI_0_2_txt.variation-s04643-h00030" link="input" register="true" transfer="true" optional="false" type="data" size="4696168"/>
  </job>
  <job id="ID00048" namespace="CyberShake" name="SeismogramSynthesis" version="1.0" runtime="47.68">
    <uses file="FFI_0_2_txt.variation-s05337-h08837" link="input" register="true" transfer="true" optional="false" type="data" size="4668966"/>
    <uses file="FFI_0_2_subfx.sgt" link="input" register="false" transfer="false" optional="false" type="data" size="217892808"/>
    <uses file="FFI_0_2_subfy.sgt" link="input" register="false" transfer="false" optional="false" type="data" size="217892808"/>
    <uses file="Seismogram_FFI_0_2_ID00048.grm" link="output" register="false" transfer="false" optional="false" type="data" size="24000"/>
  </job>
  <job id="ID00049" namespace="CyberShake" name="PeakValCalcOkaya" version="1.0" runtime="0.72">
    <uses file="Seismogram_FFI_0_2_ID00048.grm" link="input" register="false" transfer="false" optional="false" type="data" size="24000"/>
    <uses file="PeakVals_FFI_0_2_ID00048.bsa" link="output" register="false" transfer="false" optional="false" type="data" size="216"/>
  </job>
  <job id="ID00050" namespace="CyberShake" name="SeismogramSynthesis" version="1.0" runtime="59.77">
    <uses file="FFI_0_2_txt.variation-s02457-h07112" link="input" register="true" transfer="true" optional="false" type="data" size="2944830"/>
    <uses file="FFI_0_2_subfx.sgt" link="input" register="false" transfer="false" optional="false" type="data" size="296857130"/>
    <uses file="FFI_0_2_subfy.sgt" link="input" register="false" transfer="false" optional="false" type="data" size="296857130"/>
    <uses file="Seismogram_FFI_0_2_ID00050.grm" link="output" register="false" transfer="false" optional="false" type="data" size="24000"/>
  </job>
  <job id="ID00051" namespace="CyberShake" name="PeakValCalcOkaya" version="1.0" runtime="1.58">
    <uses file="Seismogram_FFI_0_2_ID00050.grm" link="input" register="false" transfer="false" optional="false" type="data" size="24000"/>
    <uses file="PeakVals_FFI_0_2_ID00050.bsa" link="output" register="false" transfer="false" optional="false" type="data" size="216"/>
  </job>
  <job id="ID00052" namespace="CyberShake" name="SeismogramSynthesis" version="1.0" runtime="44.19">
    <uses file="FFI_0_2_txt.variation-s00421-h05183" link="input" register="true" transfer="true" optional="false" type="data" size="4154308"/>
    <uses file="FFI_0_2_subfx.sgt" link="input" register="false" transfer="false" optional="false" type="data" size="130822654"/>
    <uses file="FFI_0_2_subfy.sgt" link="input" register="false" transfer="false" optional="false" type="data" size="130822654"/>
    <uses file="Seismogram_FFI_0_2_ID00052.grm" link="output" register="false" transfer="false" optional="false" type="data" size="24000"/>
  </job>
  <job id="ID00053" namespace="CyberShake" name="PeakValCalcOkaya" version="1.0" runtime="1.45">
    <uses file="Seismogram_FFI_0_2_ID00052.grm" link="input" register="false" transfer="false" optional="false" type="data" size="24000"/>
    <uses file="PeakVals_FFI_0_2_ID00052.bsa" link="output" register="false" transfer="false" optional="false" type="data" size="216"/>
  </job>
  <job id="ID00054" namespace="CyberShake" name="SeismogramSynthesis" version="1.0" runtime="41.98">
    <uses file="FFI_0_2_txt.variation-s06980-h06154" link="input" register="true" transfer="true" optional="false" type="data" size="2239439"/>
    <uses file="FFI_0_2_subfx.sgt" link="input" register="false" transfer="false" optional="false" type="data" size="164688453"/>
    <uses file="FFI_0_2_subfy.sgt" link="input" register="false" transfer="false" optional="false" type="data" size="164688453"/>
    <uses file="Seismogram_FFI_0_2_ID00054.grm" link="output" register="false" transfer="false" optional="false" type="data" size="24000"/>
  </job>
  <job id="ID00055" namespace="CyberShake" name="PeakValCalcOkaya" version="1.0" runtime="1.45">
    <uses file="Seismogram_FFI_0_2_ID00054.grm" link="input" register="false" transfer="false" optional="false" type="data" size="24000"/>
    <uses file="PeakVals_FFI_0_2_ID00054.bsa" link="output" register="false" transfer="false" optional="false" type="data" size="216"/>
  </job>
  <job id="ID00056" namespace="CyberShake" name="SeismogramSynthesis" version="1.0" runtime="25.40">
    <uses file="FFI_0_2_txt.variation-s02096-h01744" link="input" register="true" transfer="true" optional="false" type="data" size="2650344"/>
    <uses file="FFI_0_2_subfx.sgt" link="input" register="false" transfer="false" optional="false" type="data" size="210024693"/>
    <uses file="FFI_0_2_subfy.sgt" link="input" register="false" transfer="false" optional="false" type="data" size="210024693"/>
    <uses file="Seismogram_FFI_0_2_ID00056.grm" link="output" register="false" transfer="false" optional="false" type="data" size="24000"/>
  </job>
  <job id="ID00057" namespace="CyberShake" name="PeakValCalcOkaya" version="1.0" runtime="1.61">
    <uses file="Seismogram_FFI_0_2_ID00056.grm" link="input" register="false" transfer="false" optional="false" type="data" size="24000"/>
    <uses file="PeakVals_FFI_0_2_ID00056.bsa" link="output" register="false" transfer="false" optional="false" type="data" size="216"/>
  </job>
  <job id="ID00058" namespace="CyberShake" name="SeismogramSynthesis" version="1.0" runtime="34.11">
    <uses file="FFI_0_2_txt.variation-s08638-h03237" link="input" register="true" transfer="true" optional="false" type="data" size="2946421"/>
    <uses file="FFI_0_2_subfx.sgt" link="input" register="false" transfer="false" optional="false" type="data" size="344937020"/>
    <uses file="FFI_0_2_subfy.sgt" link="input" register="false" transfer="false" optional="false" type="data" size="344937020"/>
    <uses file="Seismogram_FFI_0_2_ID00058.grm" link="output" register="false" transfer="false" optional="false" type="data" size="24000"/>
  </job>
  <job id="ID00059" namespace="CyberShake" name="PeakValCalcOkaya" version="1.0" runtime="0.83">
    <uses file="Seismogram_FFI_0_2_ID00058.grm" link="input" register="false" transfer="false" optional="false" type="data" size="24000"/>
    <uses file="PeakVals_FFI_0_2_ID00058.bsa" link="output" register="false" transfer="false" optional="false" type="data" size="216"/>
  </job>
  <job id="ID00060" namespace="CyberShake" name="SeismogramSynthesis" version="1.0" runtime="31.12">
    <uses file="FFI_0_2_txt.variation-s01047-h08226" link="input" register="true" transfer="true" optional="false" type="data" size="5507637"/>
    <uses file="FFI_0_2_subfx.sgt" link="input" register="false" transfer="false" optional="false" type="data" size="221607548"/>
    <uses file="FFI_0_2_subfy.sgt" link="input" register="false" transfer="false" optional="false" type="data" size="221607548"/>
    <uses file="Seismogram_FFI_0_2_ID00060.grm" link="output" register="false" transfer="false" optional="false" type="data" size="24000"/>
  </job>
  <job id="ID00061" namespace="CyberShake" name="PeakValCalcOkaya" version="1.0" runtime="1.56">
    <uses file="Seismogram_FFI_0_2_ID00060.grm" link="input" register="false" transfer="false" optional="false" type="data" size="24000"/>
    <uses file="PeakVals_FFI_0_2_ID00060.bsa" link="output" register="false" transfer="false" optional="false" type="data" size="216"/>
  </job>
  <job id="ID00062" namespace="CyberShake" name="SeismogramSynthesis" version="1.0" runtime="43.85">
    <uses file="FFI_0_2_txt.variation-s01944-h09539" link="input" register="true" transfer="true" optional="false" type="data" size="5412373"/>
    <uses file="FFI_0_2_subfx.sgt" link="input" register="false" transfer="false" optional="false" type="data" size="133206953"/>
    <uses file="FFI_0_2_subfy.sgt" link="input" register="false" transfer="false" optional="false" type="data" size="133206953"/>
    <uses file="Seismogram_FFI_0_2_ID00062.grm" link="output" register="false" transfer="false" optional="false" type="data" size="24000"/>
  </job>
  <job id="ID00063" namespace="CyberShake" name="PeakValCalcOkaya" version="1.0" runtime="0.55">
    <uses file="Seismogram_FFI_0_2_ID00062.grm" link="input" register="false" transfer="false" optional="false" type="data" size="24000"/>
    <uses file="PeakVals_FFI_0_2_ID00062.bsa" link="output" register="false" transfer="false" optional="false" type="data" size="216"/>
  </job>
  <job id="ID00064" namespace="CyberShake" name="SeismogramSynthesis" version="1.0" runtime="30.62">
    <uses file="FFI_0_2_txt.variation-s06494-h04332" link="input" register="true" transfer="true" optional="false" type="data" size="4987217"/>
    <uses file="FFI_0_2_subfx.sgt" link="input" register="false" transfer="false" optional="false" type="data" size="191570484"/>
    <uses file="FFI_0_2_subfy.sgt" link="input" register="false" transfer="false" optional="false" type="data" size="191570484"/>
    <uses file="Seismogram_FFI_0_2_ID00064.grm" link="output" register="false" transfer="false" optional="false" type="data" size="24000"/>
  </job>
  <job id="ID00065" namespace="CyberShake" name="PeakValCalcOkaya" version="1.0" runtime="1.47">
    <uses file="Seismogram_FFI_0_2_ID00064.grm" link="input" register="false" transfer="false" optional="false" type="data" size="24000"/>
    <uses file="PeakVals_FFI_0_2_ID00064.bsa" link="output" register="false" transfer="false" optional="false" type="data" size="216"/>
  </job>
  <job id="ID00066" namespace="CyberShake" name="SeismogramSynthesis" version="1.0" runtime="50.97">
    <uses file="FFI_0_2_txt.variation-s02313-h05672" link="input" register="true" transfer="true" optional="false" type="data" size="5273762"/>
    <uses file="FFI_0_2_subfx.sgt" link="input" register="false" transfer="false" optional="false" type="data" size="117334391"/>
    <uses file="FFI_0_2_subfy.sgt" link="input" register="false" transfer="false" optional="false" type="data" size="117334391"/>
    <uses file="Seismogram_FFI_0_2_ID00066.grm" link="output" register="false" transfer="false" optional="false" type="data" size="24000"/>
  </job>
  <job id="ID00067" namespace="CyberShake" name="PeakValCalcOkaya" version="1.0" runtime="1.28">
    <uses file="Seismogram_FFI_0_2_ID00066.grm" link="input" register="false" transfer="false" optional="false" type="data" size="24000"/>
    <uses file="PeakVals_FFI_0_2_ID00066.bsa" link="output" register="false" transfer="false" optional="false" type="data" size="216"/>
  </job>
  <job id="ID00068" namespace="CyberShake" name="SeismogramSynthesis" version="1.0" runtime="58.25">
    <uses file="FFI_0_2_txt.variation-s09747-h03215" link="input" register="true" transfer="true" optional="false" type="data" size="3685465"/>
    <uses file="FFI_0_2_subfx.sgt" link="input" register="false" transfer="false" optional="false" type="data" size="259547936"/>
    <uses file="FFI_0_2_subfy.sgt" link="input" register="false" transfer="false" optional="false" type="data" size="259547936"/>
    <uses file="Seismogram_FFI_0_2_ID00068.grm" link="output" register="false" transfer="false" optional="false" type="data" size="24000"/>
  </job>
  <job id="ID00069" namespace="CyberShake" name="PeakValCalcOkaya" version="1.0" runtime="0.75">
    <uses file="Seismogram_FFI_0_2_ID00068.grm" link="input" register="false" transfer="false" optional="false" type="data" size="24000"/>
    <uses file="PeakVals_FFI_0_2_ID00068.bsa" link="output" register="false" transfer="false" optional="false" type="data" size="216"/>
  </job>
  <job id="ID00070" namespace="CyberShake" name="SeismogramSynthesis" version="1.0" runtime="29.97">
    <uses file="FFI_0_2_txt.variation-s08344-h03408" link="input" register="true" transfer="true" optional="false" type="data" size="2374994"/>
    <uses file="FFI_0_2_subfx.sgt" link="input" register="false" transfer="false" optional="false" type="data" size="128531369"/>
    <uses file="FFI_0_2_subfy.sgt" link="input" register="false" transfer="false" optional="false" type="data" size="128531369"/>
    <uses file="Seismogram_FFI_0_2_ID00070.grm" link="output" register="false" transfer="false" optional="false" type="data" size="24000"/>
  </job>
  <job id="ID00071" namespace="CyberShake" name="PeakValCalcOkaya" version="1.0" runtime="1.27">
    <uses file="Seismogram_FFI_0_2_ID00070.grm" link="input" register="false" transfer="false" optional="false" type="data" size="24000"/>
    <uses file="PeakVals_FFI_0_2_ID00070.bsa" link="output" register="false" transfer="false" optional="false" type="data" size="216"/>
  </job>
  <job id="ID00072" namespace="CyberShake" name="SeismogramSynthesis" version="1.0" runtime="47.95">
    <uses file="FFI_0_2_txt.variation-s01770-h02254" link="input" register="true" transfer="true" optional="false" type="data" size="3519947"/>
    <uses file="FFI_0_2_subfx.sgt" link="input" register="false" transfer="false" optional="false" type="data" size="292103838"/>
    <uses file="FFI_0_2_subfy.sgt" link="input" register="false" transfer="false" optional="false" type="data" size="292103838"/>
    <uses file="Seismogram_FFI_0_2_ID00072.grm" link="output" register="false" transfer="false" optional="false" type="data" size="24000"/>
  </job>
  <job id="ID00073" namespace="CyberShake" name="PeakValCalcOkaya" version="1.0" runtime="1.57">
    <uses file="Seismogram_FFI_0_2_ID00072.grm" link="input" register="false" transfer="false" optional="false" type="data" size="24000"/>
    <uses file="PeakVals_FFI_0_2_ID00072.bsa" link="output" register="false" transfer="false" optional="false" type="data" size="216"/>
  </job>
  <job id="ID00074" namespace="CyberShake" name="SeismogramSynthesis" version="1.0" runtime="28.13">
    <uses file="FFI_0_2_txt.variation-s08766-h02449" link="input" register="true" transfer="true" optional="false" type="data" size="5006827"/>
    <uses file="FFI_0_2_subfx.sgt" link="input" register="false" transfer="false" optional="false" type="data" size="122262078"/>
    <uses file="FFI_0_2_subfy.sgt" link="input" register="false" transfer="false" optional="false" type="data" size="122262078"/>
    <uses file="Seismogram_FFI_0_2_ID00074.grm" link="output" register="false" transfer="false" optional="false" type="data" size="24000"/>
  </job>
  <job id="ID00075" namespace="CyberShake" name="PeakValCalcOkaya" version="1.0" runtime="0.66">
    <uses file="Seismogram_FFI_0_2_ID00074.grm" link="input" register="false" transfer="false" optional="false" type="data" size="24000"/>
    <uses file="PeakVals_FFI_0_2_ID00074.bsa" link="output" register="false" transfer="false" optional="false" type="data" size="216"/>
  </job>
  <job id="ID00076" namespace="CyberShake" name="SeismogramSynthesis" version="1.0" runtime="62.74">
    <uses file="FFI_0_2_txt.variation-s03294-h04090" link="input" register="true" transfer="true" optional="false" type="data" size="4455059"/>
    <uses file="FFI_0_2_subfx.sgt" link="input" register="false" transfer="false" optional="false" type="data" size="156349586"/>
    <uses file="FFI_0_2_subfy.sgt" link="input" register="false" transfer="false" optional="false" type="data" size="156349586"/>
    <uses file="Seismogram_FFI_0_2_ID00076.grm" link="output" register="false" transfer="false" optional="false" type="data" size="24000"/>
  </job>
  <job id="ID00077" namespace="CyberShake" name="PeakValCalcOkaya" version="1.0" runtime="0.66">
    <uses file="Seismogram_FFI_0_2_ID00076.grm" link="input" register="false" transfer="false" optional="false" type="data" size="24000"/>
    <uses file="PeakVals_FFI_0_2_ID00076.bsa" link="output" register="false" transfer="false" optional="false" type="data" size="216"/>
  </job>
  <job id="ID00078" namespace="CyberShake" name="SeismogramSynthesis" version="1.0" runtime="28.42">
    <uses file="FFI_0_2_txt.variation-s02139-h03890" link="input" register="true" transfer="true" optional="false" type="data" size="3735850"/>
    <uses file="FFI_0_2_subfx.sgt" link="input" register="false" transfer="false" optional="false" type="data" size="253659398"/>
    <uses file="FFI_0_2_subfy.sgt" link="input" register="false" transfer="false" optional="false" type="data" size="253659398"/>
    <uses file="Seismogram_FFI_0_2_ID00078.grm" link="output" register="false" transfer="false" optional="false" type="data" size="24000"/>
  </job>
  <job id="ID00079" namespace="CyberShake" name="PeakValCalcOkaya" version="1.0" runtime="1.06">
    <uses file="Seismogram_FFI_0_2_ID00078.grm" link="input" register="false" transfer="false" optional="false" type="data" size="24000"/>
    <uses file="PeakVals_FFI_0_2_ID00078.bsa" link="output" register="false" transfer="false" optional="false" type="data" size="216"/>
  </job>
  <job id="ID00080" namespace="CyberShake" name="SeismogramSynthesis" version="1.0" runtime="40.24">
    <uses file="FFI_0_2_txt.variation-s00328-h04837" link="input" register="true" transfer="true" optional="false" type="data" size="3218214"/>
    <uses file="FFI_0_2_subfx.sgt" link="input" register="false" transfer="false" optional="false" type="data" size="224237985"/>
    <uses file="FFI_0_2_subfy.sgt" link="input" register="false" transfer="false" optional="false" type="data" size="224237985"/>
    <uses file="Seismogram_FFI_0_2_ID00080.grm" link="output" register="false" transfer="false" optional="false" type="data" size="24000"/>
  </job>
  <job id="ID00081" namespace="CyberShake" name="PeakValCalcOkaya" version="1.0" runtime="1.21">
    <uses file="Seismogram_FFI_0_2_ID00080.grm" link="input" register="false" transfer="false" optional="false" type="data" size="24000"/>
    <uses file="PeakVals_FFI_0_2_ID00080.bsa" link="output" register="false" transfer="false" optional="false" type="data" size="216"/>
  </job>
  <job id="ID00082" namespace="CyberShake" name="SeismogramSynthesis" version="1.0" runtime="36.02">
    <uses file="FFI_0_2_txt.variation-s06127-h02767" link="input" register="true" transfer="true" optional="false" type="data" size="3685848"/>
    <uses file="FFI_0_2_subfx.sgt" link="input" register="false" transfer="false" optional="false" type="data" size="153417762"/>
    <uses file="FFI_0_2_subfy.sgt" link="input" register="false" transfer="false" optional="false" type="data" size="153417762"/>
    <uses file="Seismogram_FFI_0_2_ID00082.grm" link="output" register="false" transfer="false" optional="false" type="data" size="24000"/>
  </job>
  <job id="ID00083" namespace="CyberShake" name="PeakValCalcOkaya" version="1.0" runtime="1.00">
    <uses file="Seismogram_FFI_0_2_ID00082.grm" link="input" register="false" transfer="false" optional="false" type="data" size="24000"/>
    <uses file="PeakVals_FFI_0_2_ID00082.bsa" link="output" register="false" transfer="false" optional="false" type="data" size="216"/>
  </job>
  <job id="ID00084" namespace="CyberShake" name="SeismogramSynthesis" version="1.0" runtime="60.80">
    <uses file="FFI_0_2_txt.variation-s09634-h01259" link="input" register="true" transfer="true" optional="false" type="data" size="5048085"/>
    <uses file="FFI_0_2_subfx.sgt" link="input" register="false" transfer="false" optional="false" type="data" size="292993275"/>
    <uses file="FFI_0_2_subfy.sgt" link="input" register="false" transfer="false" optional="false" type="data" size="292993275"/>
    <uses file="Seismogram_FFI_0_2_ID00084.grm" link="output" register="false" transfer="false" optional="false" type="data" size="24000"/>
  </job>
  <job id="ID00085" namespace="CyberShake" name="PeakValCalcOkaya" version="1.0" runtime="0.76">
    <uses file="Seismogram_FFI_0_2_ID00084.grm" link="input" register="false" transfer="false" optional="false" type="data" size="24000"/>
    <uses file="PeakVals_FFI_0_2_ID00084.bsa" link="output" register="false" transfer="false" optional="false" type="data" size="216"/>
  </job>
  <job id="ID00086" namespace="CyberShake" name="SeismogramSynthesis" version="1.0" runtime="45.61">
    <uses file="FFI_0_2_txt.variation-s01699-h09504" link="input" register="true" transfer="true" optional="false" type="data" size="3798613"/>
    <uses file="FFI_0_2_subfx.sgt" link="input" register="false" transfer="false" optional="false" type="data" size="254487693"/>
    <uses file="FFI_0_2_subfy.sgt" link="input" register="false" transfer="false" optional="false" type="data" size="254487693"/>
    <uses file="Seismogram_FFI_0_2_ID00086.grm" link="output" register="false" transfer="false" optional="false" type="data" size="24000"/>
  </job>
  <job id="ID00087" namespace="CyberShake" name="PeakValCalcOkaya" version="1.0" runtime="0.76">
    <uses file="Seismogram_FFI_0_2_ID00086.grm" link="input" register="false" transfer="false" optional="false" type="data" size="24000"/>
    <uses file="PeakVals_FFI_0_2_ID00086.bsa" link="output" register="false" transfer="false" optional="false" type="data" size="216"/>
  </job>
  <job id="ID00088" namespace="CyberShake" name="SeismogramSynthesis" version="1.0" runtime="27.98">
    <uses file="FFI_0_2_txt.variation-s00131-h09247" link="input" register="true" transfer="true" optional="false" type="data" size="3169276"/>
    <uses file="FFI_0_2_subfx.sgt" link="input" register="false" transfer="false" optional="false" type="data" size="165654713"/>
    <uses file="FFI_0_2_subfy.sgt" link="input" register="false" transfer="false" optional="false" type="data" size="165654713"/>
    <uses file="Seismogram_FFI_0_2_ID00088.grm" link="output" register="false" transfer="false" optional="false" type="data" size="24000"/>
  </job>
  <job id="ID00089" namespace="CyberShake" name="PeakValCalcOkaya" version="1.0" runtime="0.74">
    <uses file="Seismogram_FFI_0_2_ID00088.grm" link="input" register="false" transfer="false" optional="false" type="data" size="24000"/>
    <uses file="PeakVals_FFI_0_2_ID00088.bsa" link="output" register="false" transfer="false" optional="false" type="data" size="216"/>
  </job>
  <job id="ID00090" namespace="CyberShake" name="SeismogramSynthesis" version="1.0" runtime="38.65">
    <uses file="FFI_0_2_txt.variation-s04222-h05257" link="input" register="true" transfer="true" optional="false" type="data" size="2925863"/>
    <uses file="FFI_0_2_subfx.sgt" link="input" register="false" transfer="false" optional="false" type="data" size="167217772"/>
    <uses file="FFI_0_2_subfy.sgt" link="input" register="false" transfer="false" optional="false" type="data" size="167217772"/>
    <uses file="Seismogram_FFI_0_2_ID00090.grm" link="output" register="false" transfer="false" optional="false" type="data" size="24000"/>
  </job>
  <job id="ID00091" namespace="CyberShake" name="PeakValCalcOkaya" version="1.0" runtime="1.55">
    <uses file="Seismogram_FFI_0_2_ID00090.grm" link="input" register="false" transfer="false" optional="false" type="data" size="24000"/>
    <uses file="PeakVals_FFI_0_2_ID00090.bsa" link="output" register="false" transfer="false" optional="false" type="data" size="216"/>
  </job>
  <job id="ID00092" namespace="CyberShake" name="SeismogramSynthesis" version="1.0" runtime="33.13">
    <uses file="FFI_0_2_txt.variation-s00446-h08279" link="input" register="true" transfer="true" optional="false" type="data" size="2045722"/>
    <uses file="FFI_0_2_subfx.sgt" link="input" register="false" transfer="false" optional="false" type="data" size="261445081"/>
    <uses file="FFI_0_2_subfy.sgt" link="input" register="false" transfer="false" optional="false" type="data" size="261445081"/>
    <uses file="Seismogram_FFI_0_2_ID00092.grm" link="output" register="false" transfer="false" optional="false" type="data" size="24000"/>
  </job>
  <job id="ID00093" namespace="CyberShake" name="PeakValCalcOkaya" version="1.0" runtime="1.12">
    <uses file="Seismogram_FFI_0_2_ID00092.grm" link="input" register="false" transfer="false" optional="false" type="data" size="24000"/>
    <uses file="PeakVals_FFI_0_2_ID00092.bsa" link="output" register="false" transfer="false" optional="false" type="data" size="216"/>
  </job>
  <job id="ID00094" namespace="CyberShake" name="SeismogramSynthesis" version="1.0" runtime="26.28">
    <uses file="FFI_0_2_txt.variation-s08817-h06161" link="input" register="true" transfer="true" optional="false" type="data" size="3368447"/>
    <uses file="FFI_0_2_subfx.sgt" link="input" register="false" transfer="false" optional="false" type="data" size="308244600"/>
    <uses file="FFI_0_2_subfy.sgt" link="input" register="false" transfer="false" optional="false" type="data" size="308244600"/>
    <uses file="Seismogram_FFI_0_2_ID00094.grm" link="output" register="false" transfer="false" optional="false" type="data" size="24000"/>
  </job>
  <job id="ID00095" namespace="CyberShake" name="PeakValCalcOkaya" version="1.0" runtime="0.85">
    <uses file="Seismogram_FFI_0_2_ID00094.grm" link="input" register="false" transfer="false" optional="false" type="data" size="24000"/>
    <uses file="PeakVals_FFI_0_2_ID00094.bsa" link="output" register="false" transfer="false" optional="false" type="data" size="216"/>
  </job>
  <job id="ID00096" namespace="CyberShake" name="SeismogramSynthesis" version="1.0" runtime="41.38">
    <uses file="FFI_0_2_txt.variation-s05237-h01071" link="input" register="true" transfer="true" optional="false" type="data" size="3515678"/>
    <uses file="FFI_0_2_subfx.sgt" link="input" register="false" transfer="false" optional="false" type="data" size="166447965"/>
    <uses file="FFI_0_2_subfy.sgt" link="input" register="false" transfer="false" optional="false" type="data" size="166447965"/>
    <uses file="Seismogram_FFI_0_2_ID00096.grm" link="output" register="false" transfer="false" optional="false" type="data" size="24000"/>
  </job>
  <job id="ID00097" namespace="CyberShake" name="PeakValCalcOkaya" version="1.0" runtime="1.24">
    <uses file="Seismogram_FFI_0_2_ID00096.grm" link="input" register="false" transfer="false" optional="false" type="data" size="24000"/>
    <uses file="PeakVals_FFI_0_2_ID00096.bsa" link="output" register="false" transfer="false" optional="false" type="data" size="216"/>
  </job>
  <job id="ID00098" namespace="CyberShake" name="SeismogramSynthesis" version="1.0" runtime="38.68">
    <uses file="FFI_0_2_txt.variation-s04643-h00030" link="input" register="true" transfer="true" optional="false" type="data" size="4696168"/>
    <uses file="FFI_0_2_subfx.sgt" link="input" register="false" transfer="false" optional="false" type="data" size="327330037"/>
    <uses file="FFI_0_2_subfy.sgt" link="input" register="false" transfer="false" optional="false" type="data" size="327330037"/>
    <uses file="Seismogram_FFI_0_2_ID00098.grm" link="output" register="false" transfer="false" optional="false" type="data" size="24000"/>
  </job>
  <job id="ID00099" namespace="CyberShake" name="PeakValCalcOkaya" version="1.0" runtime="0.56">
    <uses file="Seismogram_FFI_0_2_ID00098.grm" link="input" register="false" transfer="false" optional="false" type="data" size="24000"/>
    <uses file="PeakVals_FFI_0_2_ID00098.bsa" link="output" register="false" transfer="false" optional="false" type="data" size="216"/>
  </job>
<!-- part 3: list of control-flow dependencies (may be empty) -->
  <child ref="ID00000">
    <parent ref="ID00081"/>
    <parent ref="ID00006"/>
    <parent ref="ID00028"/>
    <parent ref="ID00049"/>
    <parent ref="ID00004"/>
    <parent ref="ID00026"/>
    <parent ref="ID00069"/>
    <parent ref="ID00008"/>
    <parent ref="ID00020"/>
    <parent ref="ID00042"/>
    <parent ref="ID00063"/>
    <parent ref="ID00085"/>
    <parent ref="ID00040"/>
    <parent ref="ID00061"/>
    <parent ref="ID00083"/>
    <parent ref="ID00024"/>
    <parent ref="ID00046"/>
    <parent ref="ID00067"/>
    <parent ref="ID00089"/>
    <parent ref="ID00022"/>
    <parent ref="ID00044"/>
    <parent ref="ID00065"/>
    <parent ref="ID00087"/>
    <parent ref="ID00071"/>
    <parent ref="ID00093"/>
    <parent ref="ID00091"/>
    <parent ref="ID00016"/>
    <parent ref="ID00038"/>
    <parent ref="ID00059"/>
    <parent ref="ID00014"/>
    <parent ref="ID00036"/>
    <parent ref="ID00018"/>
    <parent ref="ID00053"/>
    <parent ref="ID00075"/>
    <parent ref="ID00097"/>
    <parent ref="ID00030"/>
    <parent ref="ID00051"/>
    <parent ref="ID00073"/>
    <parent ref="ID00095"/>
    <parent ref="ID00057"/>
    <parent ref="ID00079"/>
    <parent ref="ID00012"/>
    <parent ref="ID00034"/>
    <parent ref="ID00055"/>
    <parent ref="ID00077"/>
    <parent ref="ID00099"/>
    <parent ref="ID00010"/>
    <parent ref="ID00032"/>
  </child>
  <child ref="ID00001">
    <parent ref="ID00060"/>
    <parent ref="ID00082"/>
    <parent ref="ID00080"/>
    <parent ref="ID00005"/>
    <parent ref="ID00027"/>
    <parent ref="ID00048"/>
    <parent ref="ID00003"/>
    <parent ref="ID00025"/>
    <parent ref="ID00009"/>
    <parent ref="ID00007"/>
    <parent ref="ID00029"/>
    <parent ref="ID00064"/>
    <parent ref="ID00086"/>
    <parent ref="ID00041"/>
    <parent ref="ID00062"/>
    <parent ref="ID00084"/>
    <parent ref="ID00068"/>
    <parent ref="ID00023"/>
    <parent ref="ID00045"/>
    <parent ref="ID00066"/>
    <parent ref="ID00088"/>
    <parent ref="ID00021"/>
    <parent ref="ID00043"/>
    <parent ref="ID00070"/>
    <parent ref="ID00092"/>
    <parent ref="ID00090"/>
    <parent ref="ID00017"/>
    <parent ref="ID00039"/>
    <parent ref="ID00015"/>
    <parent ref="ID00037"/>
    <parent ref="ID00058"/>
    <parent ref="ID00019"/>
    <parent ref="ID00031"/>
    <parent ref="ID00052"/>
    <parent ref="ID00074"/>
    <parent ref="ID00096"/>
    <parent ref="ID00050"/>
    <parent ref="ID00072"/>
    <parent ref="ID00094"/>
    <parent ref="ID00013"/>
    <parent ref="ID00035"/>
    <parent ref="ID00056"/>
    <parent ref="ID00078"/>
    <parent ref="ID00011"/>
    <parent ref="ID00033"/>
    <parent ref="ID00054"/>
    <parent ref="ID00076"/>
    <parent ref="ID00098"/>
  </child>
  <child ref="ID00003">
    <parent ref="ID00002"/>
  </child>
  <child ref="ID00004">
    <parent ref="ID00003"/>
  </child>
  <child ref="ID00005">
    <parent ref="ID00002"/>
  </child>
  <child ref="ID00006">
    <parent ref="ID00005"/>
  </child>
  <child ref="ID00007">
    <parent ref="ID00002"/>
  </child>
  <child ref="ID00008">
    <parent ref="ID00007"/>
  </child>
  <child ref="ID00009">
    <parent ref="ID00002"/>
  </child>
  <child ref="ID00010">
    <parent ref="ID00009"/>
  </child>
  <child ref="ID00011">
    <parent ref="ID00002"/>
  </child>
  <child ref="ID00012">
    <parent ref="ID00011"/>
  </child>
  <child ref="ID00013">
    <parent ref="ID00002"/>
  </child>
  <child ref="ID00014">
    <parent ref="ID00013"/>
  </child>
  <child ref="ID00015">
    <parent ref="ID00002"/>
  </child>
  <child ref="ID00016">
    <parent ref="ID00015"/>
  </child>
  <child ref="ID00017">
    <parent ref="ID00002"/>
  </child>
  <child ref="ID00018">
    <parent ref="ID00017"/>
  </child>
  <child ref="ID00019">
    <parent ref="ID00002"/>
  </child>
  <child ref="ID00020">
    <parent ref="ID00019"/>
  </child>
  <child ref="ID00021">
    <parent ref="ID00002"/>
  </child>
  <child ref="ID00022">
    <parent ref="ID00021"/>
  </child>
  <child ref="ID00023">
    <parent ref="ID00002"/>
  </child>
  <child ref="ID00024">
    <parent ref="ID00023"/>
  </child>
  <child ref="ID00025">
    <parent ref="ID00002"/>
  </child>
  <child ref="ID00026">
    <parent ref="ID00025"/>
  </child>
  <child ref="ID00027">
    <parent ref="ID00002"/>
  </child>
  <child ref="ID00028">
    <parent ref="ID00027"/>
  </child>
  <child ref="ID00029">
    <parent ref="ID00002"/>
  </child>
  <child ref="ID00030">
    <parent ref="ID00029"/>
  </child>
  <child ref="ID00031">
    <parent ref="ID00002"/>
  </child>
  <child ref="ID00032">
    <parent ref="ID00031"/>
  </child>
  <child ref="ID00033">
    <parent ref="ID00002"/>
  </child>
  <child ref="ID00034">
    <parent ref="ID00033"/>
  </child>
  <child ref="ID00035">
    <parent ref="ID00002"/>
  </child>
  <child ref="ID00036">
    <parent ref="ID00035"/>
  </child>
  <child ref="ID00037">
    <parent ref="ID00002"/>
  </child>
  <child ref="ID00038">
    <parent ref="ID00037"/>
  </child>
  <child ref="ID00039">
    <parent ref="ID00002"/>
  </child>
  <child ref="ID00040">
    <parent ref="ID00039"/>
  </child>
  <child ref="ID00041">
    <parent ref="ID00002"/>
  </child>
  <child ref="ID00042">
    <parent ref="ID00041"/>
  </child>
  <child ref="ID00043">
    <parent ref="ID00002"/>
  </child>
  <child ref="ID00044">
    <parent ref="ID00043"/>
  </child>
  <child ref="ID00045">
    <parent ref="ID00002"/>
  </child>
  <child ref="ID00046">
    <parent ref="ID00045"/>
  </child>
  <child ref="ID00048">
    <parent ref="ID00047"/>
  </child>
  <child ref="ID00049">
    <parent ref="ID00048"/>
  </child>
  <child ref="ID00050">
    <parent ref="ID00047"/>
  </child>
  <child ref="ID00051">
    <parent ref="ID00050"/>
  </child>
  <child ref="ID00052">
    <parent ref="ID00047"/>
  </child>
  <child ref="ID00053">
    <parent ref="ID00052"/>
  </child>
  <child ref="ID00054">
    <parent ref="ID00047"/>
  </child>
  <child ref="ID00055">
    <parent ref="ID00054"/>
  </child>
  <child ref="ID00056">
    <parent ref="ID00047"/>
  </child>
  <child ref="ID00057">
    <parent ref="ID00056"/>
  </child>
  <child ref="ID00058">
    <parent ref="ID00047"/>
  </child>
  <child ref="ID00059">
    <parent ref="ID00058"/>
  </child>
  <child ref="ID00060">
    <parent ref="ID00047"/>
  </child>
  <child ref="ID00061">
    <parent ref="ID00060"/>
  </child>
  <child ref="ID00062">
    <parent ref="ID00047"/>
  </child>
  <child ref="ID00063">
    <parent ref="ID00062"/>
  </child>
  <child ref="ID00064">
    <parent ref="ID00047"/>
  </child>
  <child ref="ID00065">
    <parent ref="ID00064"/>
  </child>
  <child ref="ID00066">
    <parent ref="ID00047"/>
  </child>
  <child ref="ID00067">
    <parent ref="ID00066"/>
  </child>
  <child ref="ID00068">
    <parent ref="ID00047"/>
  </child>
  <child ref="ID00069">
    <parent ref="ID00068"/>
  </child>
  <child ref="ID00070">
    <parent ref="ID00047"/>
  </child>
  <child ref="ID00071">
    <parent ref="ID00070"/>
  </child>
  <child ref="ID00072">
    <parent ref="ID00047"/>
  </child>
  <child ref="ID00073">
    <parent ref="ID00072"/>
  </child>
  <child ref="ID00074">
    <parent ref="ID00047"/>
  </child>
  <child ref="ID00075">
    <parent ref="ID00074"/>
  </child>
  <child ref="ID00076">
    <parent ref="ID00047"/>
  </child>
  <child ref="ID00077">
    <parent ref="ID00076"/>
  </child>
  <child ref="ID00078">
    <parent ref="ID00047"/>
  </child>
  <child ref="ID00079">
    <parent ref="ID00078"/>
  </child>
  <child ref="ID00080">
    <parent ref="ID00047"/>
  </child>
  <child ref="ID00081">
    <parent ref="ID00080"/>
  </child>
  <child ref="ID00082">
    <parent ref="ID00047"/>
  </child>
  <child ref="ID00083">
    <parent ref="ID00082"/>
  </child>
  <child ref="ID00084">
    <parent ref="ID00047"/>
  </child>
  <child ref="ID00085">
    <parent ref="ID00084"/>
  </child>
  <child ref="ID00086">
    <parent ref="ID00047"/>
  </child>
  <child ref="ID00087">
    <parent ref="ID00086"/>
  </child>
  <child ref="ID00088">
    <parent ref="ID00047"/>
  </child>
  <child ref="ID00089">
    <parent ref="ID00088"/>
  </child>
  <child ref="ID00090">
    <parent ref="ID00047"/>
  </child>
  <child ref="ID00091">
    <parent ref="ID00090"/>
  </child>
  <child ref="ID00092">
    <parent ref="ID00047"/>
  </child>
  <child ref="ID00093">
    <parent ref="ID00092"/>
  </child>
  <child ref="ID00094">
    <parent ref="ID00047"/>
  </child>
  <child ref="ID00095">
    <parent ref="ID00094"/>
  </child>
  <child ref="ID00096">
    <parent ref="ID00047"/>
  </child>
  <child ref="ID00097">
    <parent ref="ID00096"/>
  </child>
  <child ref="ID00098">
    <parent ref="ID00047"/>
  </child>
  <child ref="ID00099">
    <parent ref="ID00098"/>
  </child>
</adag>
